ecos/__init__.py
ecos/cache.py
ecos/client.py
ecos/config.py
ecos/constants.py
ecos/exceptions.py
ecos/logging.py
ecos/metrics.py
ecos/parser.py
ecos/py.typed
ecos/types.py
ecos/indicators/__init__.py
ecos/indicators/bond.py
ecos/indicators/fiscal.py
ecos/indicators/growth.py
ecos/indicators/interest_rate.py
ecos/indicators/money.py
ecos/indicators/prices.py
ecos/indicators/stock.py
ecos_reader-0.1.5.dist-info/METADATA
ecos_reader-0.1.5.dist-info/WHEEL
ecos_reader-0.1.5.dist-info/licenses/LICENSE
ecos_reader-0.1.5.dist-info/RECORD
