Metadata-Version: 2.4
Name: ecos-reader
Version: 0.1.5
Summary: 한국은행 ECOS Open API Python 클라이언트
Project-URL: Homepage, https://github.com/choo121600/ecos-reader
Project-URL: Documentation, https://choo121600.github.io/ecos-reader/
Project-URL: Repository, https://github.com/choo121600/ecos-reader
Project-URL: Issues, https://github.com/choo121600/ecos-reader/issues
Author: yeonguk
License-Expression: MIT
License-File: LICENSE
Keywords: api,bok,economy,ecos,finance,korea,macro
Classifier: Development Status :: 3 - Alpha
Classifier: Intended Audience :: Developers
Classifier: Intended Audience :: Financial and Insurance Industry
Classifier: Intended Audience :: Science/Research
Classifier: License :: OSI Approved :: MIT License
Classifier: Operating System :: OS Independent
Classifier: Programming Language :: Python :: 3
Classifier: Programming Language :: Python :: 3.10
Classifier: Programming Language :: Python :: 3.11
Classifier: Programming Language :: Python :: 3.12
Classifier: Topic :: Office/Business :: Financial
Classifier: Topic :: Scientific/Engineering :: Information Analysis
Classifier: Typing :: Typed
Requires-Python: >=3.10
Requires-Dist: pandas>=2.0.0
Requires-Dist: python-dotenv>=1.0.0
Requires-Dist: requests>=2.28.0
Provides-Extra: dev
Requires-Dist: mypy>=1.0.0; extra == 'dev'
Requires-Dist: pre-commit>=3.0.0; extra == 'dev'
Requires-Dist: pytest-cov>=4.0.0; extra == 'dev'
Requires-Dist: pytest>=7.0.0; extra == 'dev'
Requires-Dist: responses>=0.23.0; extra == 'dev'
Requires-Dist: ruff>=0.1.0; extra == 'dev'
Provides-Extra: docs
Requires-Dist: mkdocs-material>=9.5.0; extra == 'docs'
Requires-Dist: mkdocs>=1.5.0; extra == 'docs'
